gwanicli-0.2.0.dist-info/licenses/LICENSE
qwanicli/__init__.py
qwanicli/api_client.py
qwanicli/cache.py
qwanicli/cli.py
qwanicli/config.py
qwanicli/formatter.py
qwanicli/smart_formatter.py
qwanicli/utils.py
gwanicli-0.2.0.dist-info/METADATA
gwanicli-0.2.0.dist-info/WHEEL
gwanicli-0.2.0.dist-info/entry_points.txt
gwanicli-0.2.0.dist-info/top_level.txt
gwanicli-0.2.0.dist-info/RECORD
