Metadata-Version: 2.4
Name: gwanicli
Version: 0.2.0
Summary: A command-line interface for accessing Quranic verses and translations
Home-page: https://github.com/bhantsi/gwani-cli
Author: B. Hantsi
Author-email: Hamza Danjaji <bhantsi@gmail.com>
License: MIT License
Project-URL: Homepage, https://github.com/bhantsi/gwani-cli
Project-URL: Repository, https://github.com/bhantsi/gwani-cli
Project-URL: Issues, https://github.com/bhantsi/gwani-cli/issues
Project-URL: Documentation, https://github.com/bhantsi/gwani-cli#readme
Keywords: quran,islam,cli,terminal,verses,translation
Classifier: Development Status :: 3 - Alpha
Classifier: Intended Audience :: End Users/Desktop
Classifier: License :: OSI Approved :: MIT License
Classifier: Operating System :: OS Independent
Classifier: Programming Language :: Python :: 3
Classifier: Programming Language :: Python :: 3.11
Classifier: Programming Language :: Python :: 3.12
Classifier: Topic :: Religion
Classifier: Topic :: Utilities
Classifier: Environment :: Console
Requires-Python: >=3.11
License-File: LICENSE
Requires-Dist: click>=8.0.0
Requires-Dist: requests>=2.25.0
Requires-Dist: toml>=0.10.0
Requires-Dist: arabic-reshaper>=3.0.0
Requires-Dist: python-bidi>=0.4.0
Provides-Extra: dev
Requires-Dist: pytest>=6.0; extra == "dev"
Requires-Dist: pytest-cov; extra == "dev"
Requires-Dist: black; extra == "dev"
Requires-Dist: flake8; extra == "dev"
Requires-Dist: mypy; extra == "dev"
Dynamic: author
Dynamic: home-page
Dynamic: license-file
Dynamic: requires-python
